moveread/pipelines/dfy/__init__.py
moveread/pipelines/dfy/__init__.pyi
moveread/pipelines/dfy/cli.py
moveread/pipelines/dfy/local.py
moveread/pipelines/dfy/spec.py
moveread/pipelines/dfy/core/__init__.py
moveread/pipelines/dfy/core/__init__.pyi
moveread/pipelines/dfy/core/input.py
moveread/pipelines/dfy/core/output.py
moveread_pipelines_dfy-0.5.2.dist-info/METADATA
moveread_pipelines_dfy-0.5.2.dist-info/WHEEL
moveread_pipelines_dfy-0.5.2.dist-info/entry_points.txt
moveread_pipelines_dfy-0.5.2.dist-info/top_level.txt
moveread_pipelines_dfy-0.5.2.dist-info/RECORD
